[
  {
    "title": "Calculation",
    "max_row": 3,
    "max_col": 10,
    "cells": [
      [
        {
          "addr": "A1",
          "value": "Annexure - Water Demand Calculations for Conveyor MVWS System ",
          "formula": null
        },
        {
          "addr": "B1",
          "value": null,
          "formula": null
        },
        {
          "addr": "C1",
          "value": null,
          "formula": null
        },
        {
          "addr": "D1",
          "value": null,
          "formula": null
        },
        {
          "addr": "E1",
          "value": null,
          "formula": null
        },
        {
          "addr": "F1",
          "value": null,
          "formula": null
        },
        {
          "addr": "G1",
          "value": null,
          "formula": null
        },
        {
          "addr": "H1",
          "value": null,
          "formula": null
        },
        {
          "addr": "I1",
          "value": null,
          "formula": null
        },
        {
          "addr": "J1",
          "value": null,
          "formula": null
        }
      ],
      [
        {
          "addr": "A2",
          "value": "Sr. No.",
          "formula": null
        },
        {
          "addr": "B2",
          "value": "Conveyor Length",
          "formula": null
        },
        {
          "addr": "C2",
          "value": "Conveyor Width",
          "formula": null
        },
        {
          "addr": "D2",
          "value": "Conveyor No of Belt",
          "formula": null
        },
        {
          "addr": "E2",
          "value": "Total Area (In sq. meter)\nFormula = L x W x Number of Belts",
          "formula": null
        },
        {
          "addr": "F2",
          "value": "Design Density 10.2 lpm/m2 as per IS:15325 Clause No 8.7.2",
          "formula": null
        },
        {
          "addr": "G2",
          "value": "Theoretical Water Requirement [L/Min]",
          "formula": null
        },
        {
          "addr": "H2",
          "value": "Theoretical Water Requirement [m^3/h]",
          "formula": null
        },
        {
          "addr": "I2",
          "value": null,
          "formula": null
        },
        {
          "addr": "J2",
          "value": null,
          "formula": null
        }
      ],
      [
        {
          "addr": "A3",
          "value": 1,
          "formula": null
        },
        {
          "addr": "B3",
          "value": 172,
          "formula": null
        },
        {
          "addr": "C3",
          "value": 0.8,
          "formula": null
        },
        {
          "addr": "D3",
          "value": 2,
          "formula": null
        },
        {
          "addr": "E3",
          "value": null,
          "formula": "=(B3*C3*D3)"
        },
        {
          "addr": "F3",
          "value": 10.2,
          "formula": null
        },
        {
          "addr": "G3",
          "value": null,
          "formula": "=(E3*F3)"
        },
        {
          "addr": "H3",
          "value": null,
          "formula": "=(G3*0.06)"
        },
        {
          "addr": "I3",
          "value": null,
          "formula": null
        },
        {
          "addr": "J3",
          "value": null,
          "formula": null
        }
      ]
    ]
  }
]